[
    {
        "content": "<p>Hey folks, I just published a third party <a href=\"https://highlightjs.org/\">highlight.js</a> package for Roc: <a href=\"https://www.npmjs.com/package/highlightjs-roc\">npm</a> <a href=\"https://github.com/isaacvando/highlightjs-roc\">GitHub</a>. This can be registered with highlight.js to do syntax highlighting using Node or in the browser. I wrote this so that I can use it to highlight some code in a blog post which I think will be a nice usecase because it is very lightweight. We should also be able to integrate it with Exercism to get syntax highlighting for some of the code there.</p>\n<p>This is what is looks like right now:<br>\n<a href=\"/user_uploads/22008/0g82xhsf0RClWCMiEppLGBM-/dark.png\">dark.png</a><br>\n<a href=\"/user_uploads/22008/Eme3y3Cm5nHNHn5eUezSmnp3/light.png\">light.png</a></p>\n<div class=\"message_inline_image\"><a href=\"/user_uploads/22008/0g82xhsf0RClWCMiEppLGBM-/dark.png\" title=\"dark.png\"><img data-original-dimensions=\"475x242\" src=\"/user_uploads/thumbnail/22008/0g82xhsf0RClWCMiEppLGBM-/dark.png/840x560.webp\"></a></div><div class=\"message_inline_image\"><a href=\"/user_uploads/22008/Eme3y3Cm5nHNHn5eUezSmnp3/light.png\" title=\"light.png\"><img data-original-dimensions=\"475x242\" src=\"/user_uploads/thumbnail/22008/Eme3y3Cm5nHNHn5eUezSmnp3/light.png/840x560.webp\"></a></div><p>There are many ways this can be improved so contributions are very welcome!</p>",
        "id": 469818921,
        "sender_full_name": "Isaac Van Doren",
        "timestamp": 1726193661
    },
    {
        "content": "<p>It looks awesome, thanks Isaac! I'll update Exercism to use this.</p>",
        "id": 469822079,
        "sender_full_name": "Aurélien Geron",
        "timestamp": 1726194819
    },
    {
        "content": "<p>Great!</p>",
        "id": 469822177,
        "sender_full_name": "Isaac Van Doren",
        "timestamp": 1726194853
    }
]