[
    {
        "content": "<p><a href=\"/user_uploads/22008/G1UQdIFUyx1vwusB97ejNChk/image.png\">image.png</a></p>\n<div class=\"message_inline_image\"><a href=\"/user_uploads/22008/G1UQdIFUyx1vwusB97ejNChk/image.png\" title=\"image.png\"><img data-original-content-type=\"image/png\" data-original-dimensions=\"1080x2400\" src=\"/user_uploads/thumbnail/22008/G1UQdIFUyx1vwusB97ejNChk/image.png/840x560.webp\"></a></div>",
        "id": 565396015,
        "sender_full_name": "nandi",
        "timestamp": 1766706055
    },
    {
        "content": "<p>RocFeed</p>",
        "id": 565396108,
        "sender_full_name": "Richard Feldman",
        "timestamp": 1766706339
    }
]