[
    {
        "content": "<p>Is it possible to create a new type alias based on another type alias for a tag (syntactically)?</p>\n<p>Like:</p>\n<div class=\"codehilite\"><pre><span></span><code>Fruits: [Apple, Pomegranate, Grape]\nFoods: [Fruits | Pretzel, Bread] # Foods: [Apple, Pomegranate, Grape, Pretzel, Bread]\n</code></pre></div>",
        "id": 486717949,
        "sender_full_name": "Mendel Rubin",
        "timestamp": 1733617368
    },
    {
        "content": "<p><code>Foods: [Pretzel, Bread]Fruits</code></p>",
        "id": 486718776,
        "sender_full_name": "Brendan Hansknecht",
        "timestamp": 1733618179
    },
    {
        "content": "<p>Man, I can't wait for the new syntax around this. I think I'm the future it should be:<br>\n<code>Foods : [Pretzel, Bread, ..Fruits]</code></p>",
        "id": 486718810,
        "sender_full_name": "Brendan Hansknecht",
        "timestamp": 1733618228
    },
    {
        "content": "<p>Thank you, I should've read the docs a bit better, because it also says it there (it just a bit hard to find).</p>",
        "id": 486718883,
        "sender_full_name": "Mendel Rubin",
        "timestamp": 1733618301
    },
    {
        "content": "<p><span class=\"user-mention silent\" data-user-id=\"786448\">Mendel Rubin</span> has marked this topic as resolved.</p>",
        "id": 486719038,
        "sender_full_name": "Notification Bot",
        "timestamp": 1733618491
    }
]