[
    {
        "content": "<p>I just downloaded the latest nightly release and I'm trying to figure out how to use roc from the command line but I'm having a little bit of trouble:</p>\n<div class=\"codehilite\"><pre><span></span><code>~&gt; roc --version\nroc nightly pre-release, built from commit a6bda6e on Di 16 Mai 2023 09:07:47 UTC\n\n\n~&gt; roc -h\nerror: unexpected argument &#39;-h&#39; found\n\n  tip: to pass &#39;-h&#39; as a value, use &#39;-- -h&#39;\n~&gt; roc -- -h\n\nThe current directory (/home/mikko) does not contain a main.roc file to use as a default.\n\nYou can run `roc help` for more information on how to provide a .roc file.\n\n~&gt; roc --help\nerror: unexpected argument &#39;--help&#39; found\n\n  tip: to pass &#39;--help&#39; as a value, use &#39;-- --help&#39;\n~&gt; roc -- --help\n\nThe current directory (/home/mikko) does not contain a main.roc file to use as a default.\n\nYou can run `roc help` for more information on how to provide a .roc file.\n\n~&gt; roc help\n\nThis file was not found: /home/mikko/help\n\nYou can run `roc help` for more information on how to provide a .roc file.\n</code></pre></div>\n<p>is the help under a different name or is there maybe a man page or something I could read to figure out all the different options the <code>roc</code> binary accepts?</p>",
        "id": 358945007,
        "sender_full_name": "Mikko",
        "timestamp": 1684319011
    },
    {
        "content": "<p>ah it appears the latest nightly build is broken, I went back to the one from 15th of May and <code>roc help</code> works now</p>",
        "id": 358950083,
        "sender_full_name": "Mikko",
        "timestamp": 1684320469
    },
    {
        "content": "<p>Thanks for bringing this to our attention <span class=\"user-mention\" data-user-id=\"617969\">@Mikko</span>, this is likely due to <a href=\"https://github.com/roc-lang/roc/pull/5405\">PR#5405</a>. I'll make an issue for this.</p>",
        "id": 358954250,
        "sender_full_name": "Anton",
        "timestamp": 1684321665
    },
    {
        "content": "<p><a href=\"https://github.com/roc-lang/roc/issues/5418\">#5418</a></p>",
        "id": 358956277,
        "sender_full_name": "Anton",
        "timestamp": 1684322273
    }
]