[
    {
        "content": "<p>Does/should a single line <code>if</code> work in the repl? <br>\nWhat am I doing wrong?</p>\n<div class=\"codehilite\"><pre><span></span><code>» if True then &quot;a&quot; else &quot;b&quot;\nthread &#39;main&#39; panicked at &#39;invalid cond_layout: Erroneous&#39;, crates/compiler/mono/src/ir.rs:6637:18\nnote: run with `RUST_BACKTRACE=1` environment variable to display a backtrace\n</code></pre></div>",
        "id": 351336020,
        "sender_full_name": "Matthias Toepp",
        "timestamp": 1681999417
    },
    {
        "content": "<p>you need <code>Bool.true</code> for technical reasons</p>",
        "id": 351337544,
        "sender_full_name": "Folkert de Vries",
        "timestamp": 1681999746
    },
    {
        "content": "<p><span class=\"user-mention\" data-user-id=\"281543\">@Folkert de Vries</span>  <br>\nI kind of knew Bool.true but was a thing but was thrown off because True seemed to be a value... but it makes sense  that I'm just defining a new tag on the fly named True.<br>\nThanks!</p>",
        "id": 351340144,
        "sender_full_name": "Matthias Toepp",
        "timestamp": 1682000256
    },
    {
        "content": "<p>3 messages were moved here from <a class=\"stream-topic\" data-stream-id=\"231634\" href=\"/#narrow/stream/231634-beginners/topic/Is.20Infinity.20or.20NaN\">#beginners &gt; Is Infinity or NaN</a> by <span class=\"user-mention silent\" data-user-id=\"281383\">Richard Feldman</span>.</p>",
        "id": 351368177,
        "sender_full_name": "Notification Bot",
        "timestamp": 1682006386
    },
    {
        "content": "<p>oh we should totally give a special-cased error for this!</p>",
        "id": 351368189,
        "sender_full_name": "Richard Feldman",
        "timestamp": 1682006389
    },
    {
        "content": "<p>people coming from Elm or Python likely expect it to be <code>True</code> and <code>False</code></p>",
        "id": 351368292,
        "sender_full_name": "Richard Feldman",
        "timestamp": 1682006403
    },
    {
        "content": "<p>I wrote up an issue: <a href=\"https://github.com/roc-lang/roc/issues/5318\">#5318</a></p>",
        "id": 351544762,
        "sender_full_name": "Anton",
        "timestamp": 1682066092
    }
]