[
    {
        "content": "<p>Is there a rule that the <code>Dict.insertAll</code> aka union, and the <code>Dict.keepShared</code> aka intersection use to merge values with the same key? I've been playing around in REPL and it looks like it keeps the values from the first <code>Dict</code>. Just want to confirm it's this simple to explain to users?</p>\n<p><a href=\"https://en.wikipedia.org/wiki/Union_(set_theory)\">Union</a><br>\n<a href=\"https://en.wikipedia.org/wiki/Intersection_(set_theory)\">Intersection</a></p>",
        "id": 305964161,
        "sender_full_name": "Luke Boswell",
        "timestamp": 1666679498
    },
    {
        "content": "<p><a class=\"stream-topic\" data-stream-id=\"304641\" href=\"/#narrow/stream/304641-ideas/topic/Weird.20Dict.20functions\">#ideas &gt; Weird Dict functions</a></p>",
        "id": 306036134,
        "sender_full_name": "Brendan Hansknecht",
        "timestamp": 1666706691
    },
    {
        "content": "<p>I commented about this some elsewhere.</p>",
        "id": 306036172,
        "sender_full_name": "Brendan Hansknecht",
        "timestamp": 1666706703
    }
]