[
    {
        "content": "<p>splitting this off from <a class=\"stream-topic\" data-stream-id=\"304641\" href=\"/#narrow/stream/304641-ideas/topic/discussion.20app\">#ideas &gt; discussion app</a>  - I wrote up some technical design ideas for a Roc forum (which I increasingly think we should actually build!)</p>\n<p><a href=\"https://docs.google.com/document/d/1lMwON7QlO_4-SfOSEbtrjZp2qL0eEtNaz372OJHTcRk/edit?usp=sharing\">https://docs.google.com/document/d/1lMwON7QlO_4-SfOSEbtrjZp2qL0eEtNaz372OJHTcRk/edit?usp=sharing</a></p>",
        "id": 423225836,
        "sender_full_name": "Richard Feldman",
        "timestamp": 1708830759
    },
    {
        "content": "<p>any thoughts welcome!</p>",
        "id": 423225852,
        "sender_full_name": "Richard Feldman",
        "timestamp": 1708830787
    },
    {
        "content": "<blockquote>\n<p>We can use the HTML DSL we use to render <a href=\"http://roc-lang.org\">roc-lang.org</a> for rendering, and possibly split it out into its own Roc package.</p>\n</blockquote>\n<p>I've been using <a href=\"https://github.com/Hasnep/roc-html\">https://github.com/Hasnep/roc-html</a></p>",
        "id": 423227066,
        "sender_full_name": "Luke Boswell",
        "timestamp": 1708831971
    },
    {
        "content": "<p>Sounds good. I can help too. </p>\n<p><a href=\"https://github.com/lukewilliamboswell/roc-htmx-playground\">roc-htmx-playground</a> might be a good starting point.</p>",
        "id": 423227185,
        "sender_full_name": "Luke Boswell",
        "timestamp": 1708832116
    },
    {
        "content": "<p>That design sounds great! I’m interested in helping some also</p>",
        "id": 423268647,
        "sender_full_name": "Isaac Van Doren",
        "timestamp": 1708872407
    },
    {
        "content": "<p>I really like the simplicity of the suggested stack!</p>",
        "id": 423279105,
        "sender_full_name": "Agus Zubiaga",
        "timestamp": 1708882592
    },
    {
        "content": "<p>I wonder for how long will it be cheaper to store the files in the server's filesystem. The suggested server with 40GB disk space does seem like it would last a while.</p>",
        "id": 423279435,
        "sender_full_name": "Agus Zubiaga",
        "timestamp": 1708882927
    },
    {
        "content": "<p>Last year, I tried <a href=\"https://www.cloudflare.com/en-gb/pg-cloudflare-r2-vs-aws-s3/\">Cloudflare R2</a> which is a cheaper alternative to S3</p>",
        "id": 423279538,
        "sender_full_name": "Agus Zubiaga",
        "timestamp": 1708883046
    },
    {
        "content": "<p>I’m also interested in helping! <span aria-label=\"blush\" class=\"emoji emoji-1f60a\" role=\"img\" title=\"blush\">:blush:</span></p>",
        "id": 423410302,
        "sender_full_name": "Jonas Schell",
        "timestamp": 1708958564
    },
    {
        "content": "<p>This sounds interesting.!You cant go wrong with Postgres, but I would start off with sqlite. It is very performant on modern hardware, it also got fulltext search even though I think Postgres version might be better. But the simplicity of sqlite  is hard to beat. Just a simple file and off you go.<br>\nIf you have to use build tools for js then <code>esbuild</code> is a solid choice,  a go binary that does all the usual web stuff.. bundling and minification without the madness.  (Phoenix in Elixir uses it by the default since JS caused to much trouble).</p>\n<p>For hosting of my pet projects I usually go with <a href=\"http://fly.io\">fly.io</a>, it is simply just great :)</p>",
        "id": 423422966,
        "sender_full_name": "Hannes Nevalainen",
        "timestamp": 1708961847
    },
    {
        "content": "<p>Regarding SQLite hosting, I think Turso looks like a great option. It seems reliable and more affordable than a comparable Postgres hosting service.</p>",
        "id": 435246779,
        "sender_full_name": "Giovanni K Bonetti",
        "timestamp": 1713982283
    },
    {
        "content": "<p>I was thinking that Turso could be a good option for this project also. It has an HTTP interface so we could integrate with it easily. That being said, it would be nice to put roc-pg to use in a larger project.</p>",
        "id": 435263548,
        "sender_full_name": "Isaac Van Doren",
        "timestamp": 1713988971
    }
]